monocypher.cpython-39-x86_64-linux-gnu.so
pymonocypher-4.0.2.3.dist-info/WHEEL
pymonocypher-4.0.2.3.dist-info/LICENSE.txt
pymonocypher-4.0.2.3.dist-info/top_level.txt
pymonocypher-4.0.2.3.dist-info/RECORD
pymonocypher-4.0.2.3.dist-info/METADATA
