Metadata-Version: 2.1
Name: pymonocypher
Version: 4.0.2.3
Summary: Python ctypes bindings to the Monocypher library
Home-page: https://github.com/jetperch/pymonocypher
Author: Jetperch LLC
Author-email: joulescope-dev@jetperch.com
License: BSD 2-clause
Project-URL: Bug Reports, https://github.com/jetperch/pymonocypher/issues
Project-URL: Source, https://github.com/jetperch/pymonocypher/
Keywords: cryto cryptography monocypher chacha blake2b 25519
Classifier: Development Status :: 5 - Production/Stable
Classifier: Intended Audience :: Developers
Classifier: License :: OSI Approved :: BSD License
Classifier: License :: CC0 1.0 Universal (CC0 1.0) Public Domain Dedication
Classifier: Natural Language :: English
Classifier: Topic :: Security :: Cryptography
Classifier: Programming Language :: Python :: 3.9
Classifier: Programming Language :: Python :: 3.10
Classifier: Programming Language :: Python :: 3.11
Classifier: Programming Language :: C
Requires-Python: ~=3.9
License-File: LICENSE.txt
Requires-Dist: numpy >=1.23
